almo.cpython-312-darwin.so
almo-0.0.0.dist-info/LICENSE
almo-0.0.0.dist-info/METADATA
almo-0.0.0.dist-info/WHEEL
almo-0.0.0.dist-info/top_level.txt
almo-0.0.0.dist-info/RECORD
