Metadata-Version: 2.1
Name: almo
Version: 0.0.0
Home-page: https://github.com/abap34/ALMO
Author: ['abap34', 'ebi-fly13', 'noya2']
Requires: pybind11
License-File: LICENSE
